cumd/__init__.py
cumd/cumd.py
cumd/cuxml.py
cumd/test/test_cumd.py
cumd/test/test_cuxml.py
cumd-1.6.0.dist-info/LICENSE
cumd-1.6.0.dist-info/METADATA
cumd-1.6.0.dist-info/WHEEL
cumd-1.6.0.dist-info/entry_points.txt
cumd-1.6.0.dist-info/top_level.txt
cumd-1.6.0.dist-info/RECORD
