Metadata-Version: 2.2
Name: cumd
Version: 1.6.0
Summary: Church Slavonic extensions to Markdown
Author-email: Mike Kroutikov <pgmmpk@gmail.com>
Maintainer-email: Mike Kroutikov <pgmmpk@gmail.com>
License: MIT
Project-URL: Homepage, https://github.com/slavonic/cumd/
Project-URL: Source, https://github.com/slavonic/cumd/
Keywords: church slavonic,markdown
Classifier: Development Status :: 4 - Beta
Classifier: Intended Audience :: Developers
Classifier: Intended Audience :: Education
Classifier: Intended Audience :: Religion
Classifier: Intended Audience :: Science/Research
Classifier: License :: OSI Approved :: MIT License
Classifier: Programming Language :: Python :: 3
Classifier: Programming Language :: Python :: 3.9
Classifier: Programming Language :: Python :: 3.10
Classifier: Programming Language :: Python :: 3.11
Classifier: Programming Language :: Python :: 3.12
Classifier: Programming Language :: Python :: 3.13
Classifier: Programming Language :: Python :: 3 :: Only
Requires-Python: >=3.8
License-File: LICENSE
Requires-Dist: markdown>=3.7
Requires-Dist: lxml
Requires-Dist: lxmlx
